pascalobistrot/__init__.py
pascalobistrot/main.py
pascalobistrot-0.1.0.dist-info/METADATA
pascalobistrot-0.1.0.dist-info/WHEEL
pascalobistrot-0.1.0.dist-info/RECORD
